[
    {"label": "Afghanistan Time", "value": "Asia/Kabul"},
    {"label": "Alma-Ata Time", "value": "Asia/Almaty"},
    {"label": "Arabia Standard Time", "value": "Asia/Baghdad"},
    {"label": "Armenia Time", "value": "Asia/Yerevan"},
    {"label": "Azerbaijan Time", "value": "Asia/Baku"},
    {"label": "Irkutsk Time", "value": "Asia/Irkutsk"},
    {"label": "Iran Standard Time", "value": "Asia/Tehran"},
    {"label": "Israel Standard Time", "value": "Asia/Jerusalem"},
    {"label": "Kyrgyzstan Time", "value": "Asia/Bishkek"},
    {"label": "Krasnoyarsk Time", "value": "Asia/Krasnoyarsk"},
    {"label": "Magdan Time", "value": "Asia/Magadan"},
    {"label": "Omsk Time", "value": "Asia/Omsk"},
    {"label": "Oral Time", "value": "Asia/Oral"},
    {"label": "Pakistan Standard Time", "value": "Asia/Karachi"},
    {"label": "Tajikistan Time", "value": "Asia/Dushanbe"},
    {"label": "Turkmenistan Time", "value": "Asia/Ashkhabad"},
    {"label": "Uzbekistan Time", "value": "Asia/Samarkand"},
    {"label": "Yekaterinburg Time", "value": "Asia/Yekaterinburg"}
]